policyguard/Dockerfile
policyguard/__init__.py
policyguard/policyguard.py
policyguard/default/access_policy.rego
policyguard/default/backup_policy.rego
policyguard/default/encryption_policy.rego
policyguard/default/network_policy.rego
policyguard/default/password_policy.rego
PolicyGuard-0.1.0.dist-info/LICENSE
PolicyGuard-0.1.0.dist-info/METADATA
PolicyGuard-0.1.0.dist-info/WHEEL
PolicyGuard-0.1.0.dist-info/entry_points.txt
PolicyGuard-0.1.0.dist-info/top_level.txt
PolicyGuard-0.1.0.dist-info/RECORD
